LICENSE
README.md
pyproject.toml
setup.cfg
setup.py
turbo_potato/__init__.py
turbo_potato/configfile.py
turbo_potato/turbo_potato.py
turbo_potato.egg-info/PKG-INFO
turbo_potato.egg-info/SOURCES.txt
turbo_potato.egg-info/dependency_links.txt
turbo_potato.egg-info/entry_points.txt
turbo_potato.egg-info/top_level.txt
turbo_potato.egg-info/zip-safe