Metadata-Version: 2.1
Name: turbo-potato
Version: 0.4
Summary: Compress videos to a specific file size on Windows so that they can be uploaded using the Discord free tier
Home-page: https://github.com/rpecka/turbo-potato
Author: Russell Pecka
Author-email: russell@pecka.xyz
License: MIT
Keywords: discord video ffmpeg compression
License-File: LICENSE
